TestProjects/BMI_Module.py
TestProjects/currentpage_bmi.py
TestProjects-0.0.0.1.dist-info/METADATA
TestProjects-0.0.0.1.dist-info/WHEEL
TestProjects-0.0.0.1.dist-info/top_level.txt
TestProjects-0.0.0.1.dist-info/RECORD
